Workbook

Sheet Slide1_Equities
A1: Equities
A2: All five markets on one trailing multiple from a single provider, then Japan and Taiwan against their own history because only those two exchanges publish enough of it.
A6: Market | B6: Trailing P/E | C6: P/B | D6: Via | Y6: Statistic | Z6: Value
A7: China | B7: 13.99 | C7: 1.7 | D7: MCHI | Y7: Latest PER | Z7: ='JPX_Valuation'!$B$85
A8: Hong Kong | B8: 18.47 | C8: 1.22 | D8: EWH | Y8: 5y mean | Z8: =AVERAGE('JPX_Valuation'!$B$26:$B$85)
A9: Korea | B9: 17.57 | C9: 1.65 | D9: EWY | Y9: 5y SD | Z9: =STDEV('JPX_Valuation'!$B$26:$B$85)
A10: Japan | B10: 19.01 | C10: 2.02 | D10: EWJ | Y10: SD from mean | Z10: =IFERROR(($Z$7-$Z$8)/$Z$9,"")
A11: Taiwan | B11: 27.25 | C11: 4.47 | D11: EWT | Y11: 5y low | Z11: =MIN('JPX_Valuation'!$B$26:$B$85)
Y12: 5y high | Z12: =MAX('JPX_Valuation'!$B$26:$B$85)
A13: Market | B13: Now | C13: 5y mean | D13: 5y SD | E13: To +1SD | F13: To -1SD
A14: Japan, JPX simple average | B14: ='JPX_Valuation'!$B$85 | C14: =AVERAGE('JPX_Valuation'!$B$26:$B$85) | D14: =STDEV('JPX_Valuation'!$B$26:$B$85) | E14: =$D14 | F14: =$D14
A15: Taiwan, TWSE median | B15: ='TWSE_Valuation'!$C$85 | C15: =AVERAGE('TWSE_Valuation'!$C$26:$C$85) | D15: =STDEV('TWSE_Valuation'!$C$26:$C$85) | E15: =$D15 | F15: =$D15
A17: Sector | B17: EPS 12m change, %
A18: Machinery | B18: =IFERROR(('JPX_Valuation'!$I$85/'JPX_Valuation'!$I$73-1)*100,"")
A19: Electric appliances | B19: =IFERROR(('JPX_Valuation'!$J$85/'JPX_Valuation'!$J$73-1)*100,"")
A20: Transport equipment | B20: =IFERROR(('JPX_Valuation'!$K$85/'JPX_Valuation'!$K$73-1)*100,"")
A21: Chemicals | B21: =IFERROR(('JPX_Valuation'!$L$85/'JPX_Valuation'!$L$73-1)*100,"")
A22: Iron and steel | B22: =IFERROR(('JPX_Valuation'!$M$85/'JPX_Valuation'!$M$73-1)*100,"")
A23: Banks | B23: =IFERROR(('JPX_Valuation'!$N$85/'JPX_Valuation'!$N$73-1)*100,"")
A25: All five multiples are trailing, on the fund rather than the index, and come from one provider so the comparison is a single definition applied five times. The five year band is drawn only for Japan and Taiwan: those two exchanges publish enough history to compute one, and their figures are on their own definitions, JPX a simple average across companies and TWSE a median, so read each against its own mean and not against the other. Sector growth is realised, not forecast. See the Gaps sheet for what a forward multiple would need.

Sheet Slide2_FixedIncome
A1: Fixed income
A2: Real yields where both legs are public, the wage round against prices, and each curve against its own five year range.
A6: Market | B6: Nominal 10y | C6: Core CPI, yoy | D6: Real 10y | E6: Source
A7: Japan 10y | B7: ='Free_Rates'!$C$559 | C7: 2 | D7: =IF(OR($B7="",$C7=""),"",$B7-$C7) | E7: MOF daily curve, and the July core-core print
A8: Korea 10y | B8: ='Free_Rates'!$G$559 | D8: =IF(OR($B8="",$C8=""),"",$B8-$C8) | E8: Nominal from FRED, monthly and about 2 months stale. No open core CPI, so no real yield.
A9: China 10y | D9: =IF(OR($B9="",$C9=""),"",$B9-$C9) | E9: No open publisher for either leg
A10: Hong Kong 10y | D10: =IF(OR($B10="",$C10=""),"",$B10-$C10) | E10: No open publisher for either leg
A11: Taiwan 10y | D11: =IF(OR($B11="",$C11=""),"",$B11-$C11) | E11: No open publisher for either leg
A13: Market | B13: Nominal 10y, %
A14: Japan | B14: ='Free_Rates'!$C$559
A15: Korea | B15: ='Free_Rates'!$G$559
A16: United States | B16: ='Free_Rates'!$F$559
A17: Euro area AAA | B17: ='Free_Rates'!$J$559
A20: Year | B20: Shunto, % | C20: Core-core CPI, yoy %
A21: 2021 | B21: 1.78
A22: 2022 | B22: 2.07
A23: 2023 | B23: 3.58
A24: 2024 | B24: 5.1
A25: 2025 | B25: 5.25
A26: 2026 | B26: 5.01 | C26: 2
A27: Only two core-core prints could be sourced openly, June and July 2026, so the CPI line is those points and not a series. The OIS-implied policy path the brief asked for is dealer data with no open equivalent and is not drawn.
A29: Curve | B29: Current, bp | C29: 5y low | D29: 5y high | E29: To high | F29: To low
A30: JGB 2s10s | B30: ='Free_Rates'!$M$559 | C30: =MIN('Free_Rates'!$M$299:$M$559) | D30: =MAX('Free_Rates'!$M$299:$M$559) | E30: =MAX($D30-$B30,0) | F30: =MAX($B30-$C30,0)
A31: JGB 10s30s | B31: ='Free_Rates'!$N$559 | C31: =MIN('Free_Rates'!$N$299:$N$559) | D31: =MAX('Free_Rates'!$N$299:$N$559) | E31: =MAX($D31-$B31,0) | F31: =MAX($B31-$C31,0)
A32: UST 2s10s | B32: ='Free_Rates'!$O$559 | C32: =MIN('Free_Rates'!$O$299:$O$559) | D32: =MAX('Free_Rates'!$O$299:$O$559) | E32: =MAX($D32-$B32,0) | F32: =MAX($B32-$C32,0)
A33: Euro AAA 2s10s | B33: ='Free_Rates'!$P$559 | C33: =MIN('Free_Rates'!$P$299:$P$559) | D33: =MAX('Free_Rates'!$P$299:$P$559) | E33: =MAX($D33-$B33,0) | F33: =MAX($B33-$C33,0)
A35: KTB 3s10s is not drawn: Korea publishes no open 3y series. The euro leg is the ECB's euro area AAA curve, which is dominated by Bunds but is not identical to them.

Sheet Slide3_CrossAsset
A1: Cross-asset
A2: What Japanese equity pays over the JGB, against its own history, and the resulting book.
A6: Measure | B6: Value
A7: Earnings yield, % | B7: ='JPX_Valuation'!$E$85
A8: JGB 10y, % | B8: ='JPX_Valuation'!$F$85
A9: Equity risk premium, pp | B9: ='JPX_Valuation'!$G$85
A10: Percentile since 2020 | B10: =IFERROR(COUNTIF('JPX_Valuation'!$G$7:$G$85,"<"&$B$9)/COUNT('JPX_Valuation'!$G$7:$G$85)*100,"")
A11: Months observed | B11: =COUNT('JPX_Valuation'!$G$7:$G$85)
A12: Lowest since 2020 | B12: =MIN('JPX_Valuation'!$G$7:$G$85)
A13: Highest since 2020 | B13: =MAX('JPX_Valuation'!$G$7:$G$85)
A16: The book
A17: Exposure | B17: Call | C17: Why
A18: China / HK equity | B18: Neutral | C18: Cheap on every screen and policy is supportive, but it is the most tariff-exposed earnings base in the region. Cheapness is not a catalyst.
A19: Korea equity | B19: Underweight | C19: Terminal value, not near-term earnings, is the question after DUV. Largest energy import bill in the region and defensive BoK tightening.
A20: Taiwan equity | B20: Underweight | C20: Same AI concentration as Korea with less valuation cushion. The tariff pass-through lands on the electronics supply chain.
A21: Japan equity | B21: Overweight | C21: The only market where policy normalisation expands earnings rather than compressing them. Banks and domestic demand, not the index.
A22: Japan duration | B22: Underweight | C22: The other side of the same trade. Normalisation plus super-long supply against a demand base whose duration need is largely met.
A23: China duration | B23: Overweight | C23: The one place in the region with a genuine disinflation problem, so real yields are high and the policy bias is one way. It also hedges the equity underweight above.
A25: The calls are judgement, not measurement. Say so out loud before the panel asks. Only Japan is drawn above because it is the only market in the set with an openly published multiple.

Sheet JPX_Valuation
A1: Japanese valuation, from the Tokyo exchange
A2: Monthly. Simple average trailing PER, PBR and earnings per share for the Prime market, formerly the First Section. Trailing on reported earnings, not a forward consensus multiple.
A6: Month | B6: Market PER | C6: Market PBR | D6: Market EPS | E6: Earnings yield % | F6: JGB 10y | G6: ERP, pp | H6: EPS 12m change % | I6: Machinery EPS | J6: Electric appliances EPS | K6: Transport equipment EPS | L6: Chemicals EPS | M6: Iron and steel EPS | N6: Banks EPS | P6: 5y mean | Q6: Mean +1SD | R6: Mean -1SD
A7: 2020-01 | B7: 17.2 | C7: 1.2 | D7: 130.72 | E7: =IFERROR(100/$B7,"") | F7: -0.061 | G7: =IFERROR($E7-$F7,"") | I7: 161.96 | J7: 141.8 | K7: 130.7 | L7: 158.44 | M7: 137.5 | N7: 180.61
A8: 2020-02 | B8: 14.9 | C8: 1 | D8: 130.49 | E8: =IFERROR(100/$B8,"") | F8: -0.153 | G8: =IFERROR($E8-$F8,"") | I8: 160.22 | J8: 141.75 | K8: 130.7 | L8: 158.78 | M8: 137.5 | N8: 180.56
A9: 2020-03 | B9: 14.5 | C9: 1 | D9: 127.75 | E9: =IFERROR(100/$B9,"") | F9: 0.024 | G9: =IFERROR($E9-$F9,"") | I9: 150.22 | J9: 137.53 | K9: 129.52 | L9: 152.94 | M9: 133.85 | N9: 180.58
A10: 2020-04 | B10: 15.3 | C10: 1 | D10: 127.63 | E10: =IFERROR(100/$B10,"") | F10: -0.02 | G10: =IFERROR($E10-$F10,"") | I10: 150.23 | J10: 137.45 | K10: 129.52 | L10: 153.34 | M10: 133.85 | N10: 180.97
A11: 2020-05 | B11: 16.6 | C11: 1.1 | D11: 127.08 | E11: =IFERROR(100/$B11,"") | F11: 0.009 | G11: =IFERROR($E11-$F11,"") | I11: 151.96 | J11: 136.13 | K11: 129.9 | L11: 153.21 | M11: 133.85 | N11: 181.1
A12: 2020-06 | B12: 19.6 | C12: 1.1 | D12: 107.04 | E12: =IFERROR(100/$B12,"") | F12: 0.02 | G12: =IFERROR($E12-$F12,"") | I12: 107.51 | J12: 95.69 | K12: 20.36 | L12: 124.7 | M12: 58.49 | N12: 118.79
A13: 2020-07 | B13: 18.8 | C13: 1.1 | D13: 106.31 | E13: =IFERROR(100/$B13,"") | F13: 0.018 | G13: =IFERROR($E13-$F13,"") | I13: 107.51 | J13: 91.92 | K13: 20.37 | L13: 124.24 | M13: 58.49 | N13: 118.79
A14: 2020-08 | B14: 20.1 | C14: 1.1 | D14: 106.4 | E14: =IFERROR(100/$B14,"") | F14: 0.065 | G14: =IFERROR($E14-$F14,"") | I14: 107.52 | J14: 91.84 | K14: 20.37 | L14: 124.11 | M14: 58.49 | N14: 118.79
A15: 2020-09 | B15: 21.2 | C15: 1.2 | D15: 105.46 | E15: =IFERROR(100/$B15,"") | F15: 0.02 | G15: =IFERROR($E15-$F15,"") | I15: 107.77 | J15: 90.19 | K15: 20.37 | L15: 123.32 | M15: 58.1 | N15: 122.18
A16: 2020-10 | B16: 20.3 | C16: 1.1 | D16: 105.34 | E16: =IFERROR(100/$B16,"") | F16: 0.041 | G16: =IFERROR($E16-$F16,"") | I16: 108.14 | J16: 90.25 | K16: 17.17 | L16: 123.31 | M16: 58.1 | N16: 122.18
A17: 2020-11 | B17: 22.2 | C17: 1.2 | D17: 104.13 | E17: =IFERROR(100/$B17,"") | F17: 0.035 | G17: =IFERROR($E17-$F17,"") | I17: 107.52 | J17: 90.36 | K17: 17.17 | L17: 123.3 | M17: 58.1 | N17: 122.18
A18: 2020-12 | B18: 22.6 | C18: 1.3 | D18: 103.44 | E18: =IFERROR(100/$B18,"") | F18: 0.027 | G18: =IFERROR($E18-$F18,"") | I18: 107.79 | J18: 89.8 | K18: 17.13 | L18: 122.71 | M18: 58.1 | N18: 122.18
A19: 2021-01 | B19: 22.8 | C19: 1.3 | D19: 102.26 | E19: =IFERROR(100/$B19,"") | F19: 0.056 | G19: =IFERROR($E19-$F19,"") | H19: =IFERROR(($D19/$D7-1)*100,"") | I19: 107.81 | J19: 87.82 | K19: 17.13 | L19: 120.76 | M19: 58.1 | N19: 122.18
A20: 2021-02 | B20: 23.2 | C20: 1.3 | D20: 101.28 | E20: =IFERROR(100/$B20,"") | F20: 0.168 | G20: =IFERROR($E20-$F20,"") | H20: =IFERROR(($D20/$D8-1)*100,"") | I20: 101.65 | J20: 87.76 | K20: 17.13 | L20: 120.41 | M20: 58.1 | N20: 122.18
A21: 2021-03 | B21: 25.7 | C21: 1.3 | D21: 95.01 | E21: =IFERROR(100/$B21,"") | F21: 0.088 | G21: =IFERROR($E21-$F21,"") | H21: =IFERROR(($D21/$D9-1)*100,"") | I21: 95.32 | J21: 83.31 | K21: 16.29 | L21: 111.75 | M21: 61.8 | N21: 123.57
A22: 2021-04 | B22: 25.1 | C22: 1.3 | D22: 94.69 | E22: =IFERROR(100/$B22,"") | F22: 0.095 | G22: =IFERROR($E22-$F22,"") | H22: =IFERROR(($D22/$D10-1)*100,"") | I22: 95.62 | J22: 85.34 | K22: 16.43 | L22: 112 | M22: 62.06 | N22: 123.36
A23: 2021-05 | B23: 25.6 | C23: 1.3 | D23: 92.48 | E23: =IFERROR(100/$B23,"") | F23: 0.089 | G23: =IFERROR($E23-$F23,"") | H23: =IFERROR(($D23/$D11-1)*100,"") | I23: 95.88 | J23: 85.75 | K23: 16.32 | L23: 111.86 | M23: 62.06 | N23: 123.36
A24: 2021-06 | B24: 26.3 | C24: 1.2 | D24: 91.97 | E24: =IFERROR(100/$B24,"") | F24: 0.059 | G24: =IFERROR($E24-$F24,"") | H24: =IFERROR(($D24/$D12-1)*100,"") | I24: 86.89 | J24: 135.79 | K24: 42.57 | L24: 116.12 | M24: 78.17 | N24: 129.97
A25: 2021-07 | B25: 25.8 | C25: 1.2 | D25: 92.22 | E25: =IFERROR(100/$B25,"") | F25: 0.022 | G25: =IFERROR($E25-$F25,"") | H25: =IFERROR(($D25/$D13-1)*100,"") | I25: 86.88 | J25: 136.28 | K25: 42.57 | L25: 115.94 | M25: 78.17 | N25: 129.97
A26: 2021-08 | B26: 26.5 | C26: 1.3 | D26: 92.72 | E26: =IFERROR(100/$B26,"") | F26: 0.029 | G26: =IFERROR($E26-$F26,"") | H26: =IFERROR(($D26/$D14-1)*100,"") | I26: 87.39 | J26: 137.2 | K26: 42.6 | L26: 115.9 | M26: 78.17 | N26: 129.97 | P26: ='Slide1_Equities'!$Z$8 | Q26: ='Slide1_Equities'!$Z$8+'Slide1_Equities'!$Z$9 | R26: ='Slide1_Equities'!$Z$8-'Slide1_Equities'!$Z$9
A27: 2021-09 | B27: 27.1 | C27: 1.3 | D27: 92.37 | E27: =IFERROR(100/$B27,"") | F27: 0.063 | G27: =IFERROR($E27-$F27,"") | H27: =IFERROR(($D27/$D15-1)*100,"") | I27: 86.62 | J27: 135.84 | K27: 33.27 | L27: 114.87 | M27: 80.07 | N27: 126.21 | P27: ='Slide1_Equities'!$Z$8 | Q27: ='Slide1_Equities'!$Z$8+'Slide1_Equities'!$Z$9 | R27: ='Slide1_Equities'!$Z$8-'Slide1_Equities'!$Z$9
A28: 2021-10 | B28: 26.5 | C28: 1.3 | D28: 92.62 | E28: =IFERROR(100/$B28,"") | F28: 0.101 | G28: =IFERROR($E28-$F28,"") | H28: =IFERROR(($D28/$D16-1)*100,"") | I28: 82.09 | J28: 136.02 | K28: 36.36 | L28: 114.21 | M28: 80.07 | N28: 126.37 | P28: ='Slide1_Equities'!$Z$8 | Q28: ='Slide1_Equities'!$Z$8+'Slide1_Equities'!$Z$9 | R28: ='Slide1_Equities'!$Z$8-'Slide1_Equities'!$Z$9
A29: 2021-11 | B29: 24.9 | C29: 1.2 | D29: 93.58 | E29: =IFERROR(100/$B29,"") | F29: 0.079 | G29: =IFERROR($E29-$F29,"") | H29: =IFERROR(($D29/$D17-1)*100,"") | I29: 82.67 | J29: 136.02 | K29: 36.36 | L29: 114.23 | M29: 79.91 | N29: 126.37 | P29: ='Slide1_Equities'!$Z$8 | Q29: ='Slide1_Equities'!$Z$8+'Slide1_Equities'!$Z$9 | R29: ='Slide1_Equities'!$Z$8-'Slide1_Equities'!$Z$9
A30: 2021-12 | B30: 25.4 | C30: 1.2 | D30: 94.32 | E30: =IFERROR(100/$B30,"") | F30: 0.089 | G30: =IFERROR($E30-$F30,"") | H30: =IFERROR(($D30/$D18-1)*100,"") | I30: 84.62 | J30: 136.6 | K30: 36.4 | L30: 114.65 | M30: 79.91 | N30: 126.5 | P30: ='Slide1_Equities'!$Z$8 | Q30: ='Slide1_Equities'!$Z$8+'Slide1_Equities'!$Z$9 | R30: ='Slide1_Equities'!$Z$8-'Slide1_Equities'!$Z$9
A31: 2022-01 | B31: 23.5 | C31: 1.2 | D31: 94.05 | E31: =IFERROR(100/$B31,"") | F31: 0.172 | G31: =IFERROR($E31-$F31,"") | H31: =IFERROR(($D31/$D19-1)*100,"") | I31: 85.01 | J31: 137.05 | K31: 36.4 | L31: 114.86 | M31: 79.91 | N31: 126.5 | P31: ='Slide1_Equities'!$Z$8 | Q31: ='Slide1_Equities'!$Z$8+'Slide1_Equities'!$Z$9 | R31: ='Slide1_Equities'!$Z$8-'Slide1_Equities'!$Z$9
A32: 2022-02 | B32: 23.7 | C32: 1.2 | D32: 94.56 | E32: =IFERROR(100/$B32,"") | F32: 0.214 | G32: =IFERROR($E32-$F32,"") | H32: =IFERROR(($D32/$D20-1)*100,"") | I32: 88.67 | J32: 137.09 | K32: 36.45 | L32: 114.97 | M32: 79.91 | N32: 126.52 | P32: ='Slide1_Equities'!$Z$8 | Q32: ='Slide1_Equities'!$Z$8+'Slide1_Equities'!$Z$9 | R32: ='Slide1_Equities'!$Z$8-'Slide1_Equities'!$Z$9
A33: 2022-03 | B33: 22 | C33: 1.2 | D33: 102.92 | E33: =IFERROR(100/$B33,"") | F33: 0.248 | G33: =IFERROR($E33-$F33,"") | H33: =IFERROR(($D33/$D21-1)*100,"") | I33: 104.47 | J33: 148.28 | K33: 51.59 | L33: 127.73 | M33: 81.6 | N33: 127.17 | P33: ='Slide1_Equities'!$Z$8 | Q33: ='Slide1_Equities'!$Z$8+'Slide1_Equities'!$Z$9 | R33: ='Slide1_Equities'!$Z$8-'Slide1_Equities'!$Z$9
A34: 2022-04 | B34: 20.4 | C34: 1.2 | D34: 118.12 | E34: =IFERROR(100/$B34,"") | F34: 0.22 | G34: =IFERROR($E34-$F34,"") | H34: =IFERROR(($D34/$D22-1)*100,"") | I34: 122.31 | J34: 164.7 | K34: 67.34 | L34: 134.32 | M34: 90.06 | N34: 137.95 | P34: ='Slide1_Equities'!$Z$8 | Q34: ='Slide1_Equities'!$Z$8+'Slide1_Equities'!$Z$9 | R34: ='Slide1_Equities'!$Z$8-'Slide1_Equities'!$Z$9
A35: 2022-05 | B35: 19.8 | C35: 1.2 | D35: 121.92 | E35: =IFERROR(100/$B35,"") | F35: 0.236 | G35: =IFERROR($E35-$F35,"") | H35: =IFERROR(($D35/$D23-1)*100,"") | I35: 125.78 | J35: 164.18 | K35: 67.34 | L35: 134.32 | M35: 90.53 | N35: 137.95 | P35: ='Slide1_Equities'!$Z$8 | Q35: ='Slide1_Equities'!$Z$8+'Slide1_Equities'!$Z$9 | R35: ='Slide1_Equities'!$Z$8-'Slide1_Equities'!$Z$9
A36: 2022-06 | B36: 13.7 | C36: 1.1 | D36: 172.63 | E36: =IFERROR(100/$B36,"") | F36: 0.24 | G36: =IFERROR($E36-$F36,"") | H36: =IFERROR(($D36/$D24-1)*100,"") | I36: 189.52 | J36: 234.03 | K36: 151.47 | L36: 179.15 | M36: 258.24 | N36: 195.36 | P36: ='Slide1_Equities'!$Z$8 | Q36: ='Slide1_Equities'!$Z$8+'Slide1_Equities'!$Z$9 | R36: ='Slide1_Equities'!$Z$8-'Slide1_Equities'!$Z$9
A37: 2022-07 | B37: 14.4 | C37: 1.2 | D37: 172.06 | E37: =IFERROR(100/$B37,"") | F37: 0.185 | G37: =IFERROR($E37-$F37,"") | H37: =IFERROR(($D37/$D25-1)*100,"") | I37: 189.54 | J37: 234.4 | K37: 151.46 | L37: 179.14 | M37: 258.24 | N37: 195.36 | P37: ='Slide1_Equities'!$Z$8 | Q37: ='Slide1_Equities'!$Z$8+'Slide1_Equities'!$Z$9 | R37: ='Slide1_Equities'!$Z$8-'Slide1_Equities'!$Z$9
... A85: 2026-07 | B85: 18.5 | C85: 1.5 | D85: 178.36 | E85: =IFERROR(100/$B85,"") | F85: 2.801 | G85: =IFERROR($E85-$F85,"") | H85: =IFERROR(($D85/$D73-1)*100,"") | I85: 212.91 | J85: 220.45 | K85: 184.83 | L85: 167.96 | M85: 203.59 | N85: 197.14 | P85: ='Slide1_Equities'!$Z$8 | Q85: ='Slide1_Equities'!$Z$8+'Slide1_Equities'!$Z$9 | R85: ='Slide1_Equities'!$Z$8-'Slide1_Equities'!$Z$9

Sheet TWSE_Valuation
A1: Taiwanese valuation, from the Taiwan exchange
A2: Monthly. Median trailing P/E across all listed companies at month end. Loss makers publish no ratio and are excluded; the count of those included is carried alongside.
A6: Month | B6: As of | C6: Median P/E | D6: Median P/B | E6: Median yield % | F6: Companies | G6: With a P/E
A7: 2020-01 | B7: 43861 | C7: 16.105 | D7: 1.29 | E7: 4.375 | F7: 941 | G7: 750
A8: 2020-02 | B8: 43888 | C8: 16.035 | D8: 1.28 | E8: 4.5 | F8: 940 | G8: 750
A9: 2020-03 | B9: 43921 | C9: 13.8 | D9: 1.05 | E9: 5.145 | F9: 942 | G9: 763
A10: 2020-04 | B10: 43951 | C10: 15.75 | D10: 1.21 | E10: 4.47 | F10: 942 | G10: 761
A11: 2020-05 | B11: 43980 | C11: 16.84 | D11: 1.27 | E11: 4.29 | F11: 942 | G11: 717
A12: 2020-06 | B12: 44012 | C12: 17.57 | D12: 1.33 | E12: 4.21 | F12: 943 | G12: 717
A13: 2020-07 | B13: 44043 | C13: 17.515 | D13: 1.35 | E13: 4.12 | F13: 943 | G13: 718
A14: 2020-08 | B14: 44074 | C14: 17.8 | D14: 1.415 | E14: 3.94 | F14: 944 | G14: 724
A15: 2020-09 | B15: 44104 | C15: 17.48 | D15: 1.395 | E15: 4.11 | F15: 942 | G15: 723
A16: 2020-10 | B16: 44134 | C16: 17.57 | D16: 1.4 | E16: 4.05 | F16: 941 | G16: 721
A17: 2020-11 | B17: 44165 | C17: 18.12 | D17: 1.51 | E17: 3.75 | F17: 942 | G17: 738
A18: 2020-12 | B18: 44196 | C18: 18.35 | D18: 1.555 | E18: 3.67 | F18: 942 | G18: 740
... A85: 2026-07 | B85: 46234 | C85: 19.4 | D85: 1.59 | E85: 3.61 | F85: 1081 | G85: 835

Sheet Free_Rates
A1: Government yields with a public source
A2: Weekly, Friday. JGB from the MOF daily curve file, UST from FRED, euro area AAA curve from the ECB, Korea and Germany from FRED's OECD monthly long rate which runs about two months behind.
A6: Date | B6: JGB 2y | C6: JGB 10y | D6: JGB 30y | E6: UST 2y | F6: UST 10y | G6: Korea 10y | H6: Germany 10y | I6: Euro AAA 2y | J6: Euro AAA 10y | K6: HK EFN 2y | L6: HK EFB 3m | M6: JGB 2s10s | N6: JGB 10s30s | O6: UST 2s10s | P6: Euro 2s10s
A7: 42370 | B7: -0.033 | C7: 0.267 | D7: 1.282 | E7: 1.06 | F7: 2.27 | G7: 2.025 | H7: 0.4305 | K7: 0.496 | L7: 0.04 | M7: =($C7-$B7)*100 | N7: =($D7-$C7)*100 | O7: =($F7-$E7)*100 | P7: =($J7-$I7)*100
A8: 42377 | B8: -0.031 | C8: 0.23 | D8: 1.22 | E8: 0.94 | F8: 2.13 | G8: 2.025 | H8: 0.4305 | I8: -0.3933 | J8: 0.6761 | K8: 0.432 | L8: 0.04 | M8: =($C8-$B8)*100 | N8: =($D8-$C8)*100 | O8: =($F8-$E8)*100 | P8: =($J8-$I8)*100
A9: 42384 | B9: -0.03 | C9: 0.221 | D9: 1.252 | E9: 0.85 | F9: 2.03 | G9: 2.025 | H9: 0.4305 | I9: -0.3953 | J9: 0.629 | K9: 0.432 | L9: 0.1 | M9: =($C9-$B9)*100 | N9: =($D9-$C9)*100 | O9: =($F9-$E9)*100 | P9: =($J9-$I9)*100
A10: 42391 | B10: -0.021 | C10: 0.237 | D10: 1.208 | E10: 0.88 | F10: 2.07 | G10: 2.025 | H10: 0.4305 | I10: -0.4336 | J10: 0.5915 | K10: 0.826 | L10: 0.22 | M10: =($C10-$B10)*100 | N10: =($D10-$C10)*100 | O10: =($F10-$E10)*100 | P10: =($J10-$I10)*100
A11: 42398 | B11: -0.083 | C11: 0.104 | D11: 1.103 | E11: 0.76 | F11: 1.94 | G11: 2.025 | H11: 0.4305 | I11: -0.4661 | J11: 0.4394 | K11: 0.898 | L11: 0.24 | M11: =($C11-$B11)*100 | N11: =($D11-$C11)*100 | O11: =($F11-$E11)*100 | P11: =($J11-$I11)*100
A12: 42405 | B12: -0.193 | C12: 0.036 | D12: 1.11 | E12: 0.74 | F12: 1.86 | G12: 1.826 | H12: 0.1729 | I12: -0.4719 | J12: 0.4098 | K12: 0.795 | L12: 0.33 | M12: =($C12-$B12)*100 | N12: =($D12-$C12)*100 | O12: =($F12-$E12)*100 | P12: =($J12-$I12)*100
A13: 42412 | B13: -0.164 | C13: 0.086 | D13: 1.177 | E13: 0.71 | F13: 1.74 | G13: 1.826 | H13: 0.1729 | I13: -0.4979 | J13: 0.336 | K13: 0.73 | L13: 0.25 | M13: =($C13-$B13)*100 | N13: =($D13-$C13)*100 | O13: =($F13-$E13)*100 | P13: =($J13-$I13)*100
A14: 42419 | B14: -0.212 | C14: 0.016 | D14: 1.062 | E14: 0.76 | F14: 1.76 | G14: 1.826 | H14: 0.1729 | I14: -0.5034 | J14: 0.2989 | K14: 0.666 | L14: 0.14 | M14: =($C14-$B14)*100 | N14: =($D14-$C14)*100 | O14: =($F14-$E14)*100 | P14: =($J14-$I14)*100
A15: 42426 | B15: -0.236 | C15: -0.055 | D15: 0.907 | E15: 0.8 | F15: 1.76 | G15: 1.826 | H15: 0.1729 | I15: -0.52 | J15: 0.2571 | K15: 0.562 | L15: 0.06 | M15: =($C15-$B15)*100 | N15: =($D15-$C15)*100 | O15: =($F15-$E15)*100 | P15: =($J15-$I15)*100
A16: 42433 | B16: -0.203 | C16: -0.042 | D16: 0.777 | E16: 0.88 | F16: 1.88 | G16: 1.854 | H16: 0.1714 | I16: -0.5303 | J16: 0.3266 | K16: 0.661 | L16: 0.07 | M16: =($C16-$B16)*100 | N16: =($D16-$C16)*100 | O16: =($F16-$E16)*100 | P16: =($J16-$I16)*100
A17: 42440 | B17: -0.163 | C17: -0.016 | D17: 0.791 | E17: 0.97 | F17: 1.98 | G17: 1.854 | H17: 0.1714 | I17: -0.4581 | J17: 0.3697 | K17: 0.606 | L17: 0.06 | M17: =($C17-$B17)*100 | N17: =($D17-$C17)*100 | O17: =($F17-$E17)*100 | P17: =($J17-$I17)*100
A18: 42447 | B18: -0.22 | C18: -0.101 | D18: 0.475 | E18: 0.84 | F18: 1.88 | G18: 1.854 | H18: 0.1714 | I18: -0.481 | J18: 0.3021 | K18: 0.54 | L18: 0.02 | M18: =($C18-$B18)*100 | N18: =($D18-$C18)*100 | O18: =($F18-$E18)*100 | P18: =($J18-$I18)*100
A19: 42454 | B19: -0.224 | C19: -0.1 | D19: 0.523 | E19: 0.89 | F19: 1.91 | G19: 1.854 | H19: 0.1714 | I19: -0.4842 | J19: 0.2865 | K19: 0.621 | L19: 0.06 | M19: =($C19-$B19)*100 | N19: =($D19-$C19)*100 | O19: =($F19-$E19)*100 | P19: =($J19-$I19)*100
... A559: 46234 | B559: 1.507 | C559: 2.801 | D559: 3.982 | E559: 4.28 | F559: 4.75 | G559: 4.181 | H559: 2.97 | I559: 2.7608 | J559: 3.2273 | K559: 3.016 | L559: 2.69 | M559: =($C559-$B559)*100 | N559: =($D559-$C559)*100 | O559: =($F559-$E559)*100 | P559: =($J559-$I559)*100

Sheet Gaps
A1: What is not here, and why
A5: Wanted | B5: Why it is missing | C5: What to use if a terminal ever appears
A6: Forward P/E, all five markets | B6: IBES consensus is licensed. No exchange publishes a forward index multiple. Japan is drawn on the exchange's trailing PER instead. | C6: BEST_PE_RATIO with BEST_FPERIOD_OVERRIDE=1BF
A7: 3 month EPS revision ratio | B7: A revision measure needs the estimate panel itself. Nothing public carries it. Realised earnings momentum is drawn instead, which moves later than revisions do. | C7: BQL over index members on pct_chg(best_eps(fpo='1BF'),'-3M')
A8: FY26 and FY27 consensus EPS growth | B8: Forecast earnings are licensed. Realised year on year growth from JPX is drawn instead and is a different thing. | C8: BEST_EPS with 1BF and 2BF overrides
A9: OIS-implied policy path | B9: Dealer curve data with no open equivalent. | C9: JYSO1, JYSO2 and the 1y1y forward
A10: China, Hong Kong and Taiwan 10y | B10: No open daily publisher. Stooq and the OECD API sit behind bot challenges, HKMA's open API does not carry bond yields, and KRX refuses programmatic access. | C10: GCNY10YR, HKGG10Y, GVTW10YR
A11: Core CPI outside Japan | B11: FRED's OECD-sourced Asian CPI feeds were discontinued and end in April 2025 or earlier. A 15 month stale core print would make the real yield wrong rather than absent. | C11: CHEFTYOY, KRCPCORY, TWCPCORY
A12: Korea 3y, for KTB 3s10s | B12: Korea publishes no open short-tenor series and KRX blocks the data portal. | C12: GVSK3YR
A13: Five year valuation band outside Japan and Taiwan | B13: All five current multiples are drawn from iShares fund data. Only JPX and TWSE publish enough history to compute a mean and standard deviation; BlackRock publishes no history of the field. | C13: BEST_PE_RATIO with a date range
A15: Nothing above has been approximated into existence. An empty cell means no open source was found, not that the number is zero.

Sheet Notes
A1: Sources and method
A5: JPX | B5: Average PER and PBR by size and industry, one workbook a month, 79 months from January 2020. Simple average trailing PER on reported consolidated earnings for the Prime market, which was the First Section before April 2022.
A6: MOF | B6: The whole JGB curve, 1y to 40y, every business day since 1974.
A7: FRED | B7: DGS2 and DGS10 daily; Korea and Germany long rates from the OECD monthly series, about two months behind.
A8: ECB | B8: Euro area AAA government spot curve, 2y and 10y, daily.
A9: Rengo | B9: Rengo final tally. 2026 at 5.01% reported 3 July 2026, 0.24pp below 2025 and the third consecutive year above 5%.
A10: Statistics Bureau of Japan | B10: Statistics Bureau of Japan via press reporting: core-core at 2.0% year on year in July 2026, up from 1.9% in June. These two prints are the only ones sourced. FRED's Japan CPI feed ends June 2021 and the OECD API is behind a bot challenge, so the history is a Bloomberg field rather than typed.
A12: Two things the free data changes
A13: ◆ The multiple is trailing, not forward. JPX computes it on reported earnings. A forward consensus multiple is a different number and is usually lower where earnings are rising, so this exhibit reads more expensive than an IBES-based one would.
A14: ◆ Sector growth is realised, not forecast. It is the change in reported earnings per share against the same month a year earlier, which turns later than an estimate revision does.
A16: Method
A17: ◆ The JPX workbooks up to early 2022 store every figure as a literal formula, the string "=17.2" rather than the number, with no cached result. Read with data_only they come back empty, which silently produced a file where only the most recent 21 of 79 months carried data. The puller reads raw and strips the leading equals, and now fails loudly if fewer than nine in ten months carry a PER.
A18: ◆ Percentiles are written as COUNTIF over the whole column, which is the definition of the statistic spelled out and auditable in one click.
A19: ◆ The range markers are custom error bars, so the band is read off the same cells as the table beside it.
A20: ◆ The allocation calls on slide 3 are judgement. Every other number in this workbook is pulled from a named public source.
